easy_reports/__init__.py
easy_reports/base.py
easy_reports/cli.py
easy_reports/config.py
easy_reports/data.py
easy_reports/defaults.py
easy_reports/email.py
easy_reports/email_smtplib.py
easy_reports/excel.py
easy_reports/boilerplate/report.py
easy_reports-1.0.1.dist-info/LICENCE
easy_reports-1.0.1.dist-info/METADATA
easy_reports-1.0.1.dist-info/WHEEL
easy_reports-1.0.1.dist-info/entry_points.txt
easy_reports-1.0.1.dist-info/top_level.txt
easy_reports-1.0.1.dist-info/RECORD
