Metadata-Version: 2.1
Name: easy-reports
Version: 1.0.1
Summary: Simplified Report configuration, generation and distribution
Author-email: Grzegorz Gyczew <ggyczew@gmail.com>
License: MIT
Project-URL: repository, https://github.com/ggyczew/ggy_easy_reports
Project-URL: changelog, https://github.com/ggyczew/ggy_easy_reports/main/CHANGELOG.md
Classifier: Programming Language :: Python :: 3
Classifier: Operating System :: OS Independent
Requires-Python: >=3.9.0
License-File: LICENCE
Requires-Dist: pandas (>=1.5.2)
Requires-Dist: XlsxWriter (>=3.0.3)
Requires-Dist: pyarrow (>=11.0.0)
Requires-Dist: SQLAlchemy (>=2.0.4)
Requires-Dist: click (>=8.1.3)
Requires-Dist: pyodbc (>=4.0.35)
Requires-Dist: psycopg2-binary (>=2.9.5)
Requires-Dist: pymysql (>=1.0.2)
Provides-Extra: test
Requires-Dist: pytest (>=7.2.0) ; extra == 'test'
Requires-Dist: pytest-cov[all] ; extra == 'test'
